teleskope/__init__.py
teleskope/client.py
teleskope/config.py
teleskope/log.py
teleskope/server.py
teleskope/settings.py
teleskope/types.py
teleskope/ws.py
tests/__init__.py
tests/conftest.py
tests/test_client.py
tests/test_server.py
tests/test_version.py
teleskope-0.0.0a0.dist-info/LICENSE
teleskope-0.0.0a0.dist-info/METADATA
teleskope-0.0.0a0.dist-info/WHEEL
teleskope-0.0.0a0.dist-info/top_level.txt
teleskope-0.0.0a0.dist-info/RECORD
