Metadata-Version: 2.1
Name: teleskope
Version: 0.0.0a0
Summary: teleskope
Author-email: "Galileo Technologies, Inc." <team@rungalileo.io>
License: MIT
Project-URL: Documentation, https://github.com/rungalileo/teleskope
Requires-Python: >=3.10
License-File: LICENSE
Requires-Dist: fastapi (==0.89.1)
Requires-Dist: websockets (==10.4)
Requires-Dist: uvicorn (==0.20.0)
Requires-Dist: python-dotenv (==0.21.1)
Provides-Extra: dev
Requires-Dist: mypy (>=0.910) ; extra == 'dev'
Requires-Dist: black (>=21.10b0) ; extra == 'dev'
Requires-Dist: ruff (>=0.0.98) ; extra == 'dev'
Requires-Dist: pre-commit (>=2.17.0) ; extra == 'dev'
Provides-Extra: test
Requires-Dist: pytest (>=6.2.5) ; extra == 'test'
Requires-Dist: coverage (>=6.1.1) ; extra == 'test'
Requires-Dist: pytest-cov (>=3.0.0) ; extra == 'test'
